dwython/__init__.py
dwython/query.py
dwython-0.3.6.dist-info/LICENSE
dwython-0.3.6.dist-info/METADATA
dwython-0.3.6.dist-info/WHEEL
dwython-0.3.6.dist-info/top_level.txt
dwython-0.3.6.dist-info/RECORD
